<?xml version="1.0"?>
<ArrayOfShop xmlns:xsi="http://www.w3.org/2001/XMLSchema-instance" xmlns:xsd="http://www.w3.org/2001/XMLSchema">
  <Shop>
    <Name>Адик</Name>
    <Categories>
      <Category>
        <Name>Обувь</Name>
        <Products>
          <Product>
            <Name>Нормальная обувь</Name>
            <Description>фыафыа</Description>
          </Product>
          <Product>
            <Name>Ненормальная обувьsafs</Name>
            <Description>Мне нравицаasfaasf</Description>
          </Product>
          <Product>
            <Name>Кроссы рибок</Name>
            <Description>лучшие просто</Description>
          </Product>
        </Products>
      </Category>
      <Category>
        <Name>Одежда</Name>
        <Products>
          <Product>
            <Name>Одежда 1</Name>
            <Description>Очень классная</Description>
          </Product>
        </Products>
      </Category>
    </Categories>
    <Address>фыафыа</Address>
  </Shop>
  <Shop>
    <Name>Nike</Name>
    <Categories />
    <Address>ыфафыа</Address>
  </Shop>
  <Shop>
    <Name>Reebok</Name>
    <Categories />
    <Address>ыфафаф</Address>
  </Shop>
</ArrayOfShop>